AUTHORS.rst
CONTRIBUTING.rst
HISTORY.rst
LICENSE
MANIFEST.in
README.rst
setup.cfg
setup.py
authortoolkit/__init__.py
authortoolkit/agglomerator.py
authortoolkit/authortoolkit.py
authortoolkit/cluster.py
authortoolkit/config.py
authortoolkit/mention.py
authortoolkit/name_dist.py
authortoolkit/nick_names.py
authortoolkit/output.py
authortoolkit/pickle_mentions.py
authortoolkit/pickle_name_dist.py
authortoolkit/speller.py
authortoolkit/utils.py
authortoolkit.egg-info/PKG-INFO
authortoolkit.egg-info/SOURCES.txt
authortoolkit.egg-info/dependency_links.txt
authortoolkit.egg-info/not-zip-safe
authortoolkit.egg-info/top_level.txt
docs/Makefile
docs/authors.rst
docs/conf.py
docs/contributing.rst
docs/history.rst
docs/index.rst
docs/installation.rst
docs/make.bat
docs/readme.rst
docs/usage.rst
tests/__init__.py
tests/test_authortoolkit.py