Metadata-Version: 1.1
Name: authortoolkit
Version: 0.1.0
Summary: automatically determine the identities of authors in collections of publications
Home-page: https://github.com/jeff-regier/authortoolkit
Author: Jeffrey Regier
Author-email: jeff@stat.berkeley.edu
License: ISCL
Keywords: authortoolkit
Platform: UNKNOWN
Classifier: Development Status :: 2 - Pre-Alpha
Classifier: Intended Audience :: Developers
Classifier: License :: OSI Approved :: ISC License (ISCL)
Classifier: Natural Language :: English
Classifier: Programming Language :: Python :: 2
Classifier: Programming Language :: Python :: 2.7
